
{
    "contact_email":"partnership@ookamimedia.com",
    "contact_address":"Jungle Technology LLC Plot no. 386-0, Al Budoor Building-Naif, Dubai, United Arab Emirates",
 "version": "1.0",
 "sellers": [
  {
    "Seller_id": 2235,
    "Name": "KP - WM",
    "Domain": "https://dreamapps96.blogspot.com",
    "seller_type": "PUBLISHER"
  },
  {
    "Seller_id": 2236,
    "Name": "WM - Jishan Kumar KP",
    "Domain": "https://videoalldownloadpolicy.blogspot.com/",
    "seller_type": "PUBLISHER"
  },
  {
    "Seller_id": 2237,
    "Name": "WM - JP",
    "Domain": "https://creatnice01.blogspot.com",
    "seller_type": "PUBLISHER"
  },
  {
    "Seller_id": 2238,
    "Name": "WM - JP - Datha",
    "Domain": "https://adinsignia.com",
    "seller_type": "PUBLISHER"
  },
  {
    "Seller_id": 2239,
    "Name": "WM - Korat",
    "Domain": "https://squaredapps.blogspot.com",
    "seller_type": "PUBLISHER"
  },
  {
    "Seller_id": 2240,
    "Name": "WM - JP - Train",
    "Domain": "https://gredappads.blogspot.com",
    "seller_type": "PUBLISHER"
  },
  {
    "Seller_id": 2241,
    "Name": "WM - KP - Zeel",
    "Domain": "https://policyforplayerappprivacy.blogspot.com/",
    "seller_type": "PUBLISHER"
  },
  {
    "Seller_id": 2242,
    "Name": "WM - JP - Adapt",
    "Domain": "https://adoringvalley.blogspot.com",
    "seller_type": "PUBLISHER"
  },
  {
    "Seller_id": 2243,
    "Name": "WM - Korat - 2",
    "Domain": "https://decpackapps.blogspot.com",
    "seller_type": "PUBLISHER"
  },
  {
    "Seller_id": 2244,
    "Name": "WM - radha",
    "Domain": "https://videodownloadallprivacyforapp.blogspot.com/",
    "seller_type": "PUBLISHER"
  },
  {
    "Seller_id": 2245,
    "Name": "WM - KP - Creation",
    "Domain": "https://brandparmar.blogspot.com",
    "seller_type": "PUBLISHER"
  },
  {
    "Seller_id": 2247,
    "Name": "WM - KP - Constance",
    "Domain": "https://nationalgraphics2022.blogspot.com",
    "seller_type": "PUBLISHER"
  },
  {
    "Seller_id": 2251,
    "Name": "WM - Mohan",
    "Domain": "https://katnttech.blogspot.com/",
    "seller_type": "PUBLISHER"
  },
  {
    "Seller_id": 2252,
    "Name": "WM - KP - Hariahuja",
    "Domain": "https://vinagastudio.blogspot.com/",
    "seller_type": "PUBLISHER"
  },
  {
    "Seller_id": 2254,
    "Name": "WM - KP - Hiren",
    "Domain": "https://loveappstudio.blogspot.com/",
    "seller_type": "PUBLISHER"
  },
  {
    "Seller_id": 2255,
    "Name": "WM - Korat - PrankVideo",
    "Domain": "https://instamoney93.blogspot.com/",
    "seller_type": "PUBLISHER"
  },
  {
    "Seller_id": 2256,
    "Name": "WM - JP - Bootscloud",
    "Domain": "https://privacypolicy510.blogspot.com/",
    "seller_type": "PUBLISHER"
  },
  {
    "Seller_id": 2257,
    "Name": "WM - JP - Century",
    "Domain": "https://wingsswitch.blogspot.com/",
    "seller_type": "PUBLISHER"
  },
  {
    "Seller_id": 2258,
    "Name": "WM - JP - Chorasclick",
    "Domain": "https://clericepic.blogspot.com/",
    "seller_type": "PUBLISHER"  
   },
   {
    "Seller_id": 2259,
    "Name": "WM - Atrangi -JD",
    "Domain": "https://appstechconsulting.blogspot.com/",
    "seller_type": "PUBLISHER"
  },
  {
    "Seller_id": 2260,
    "Name": "WM - Kapildoshi",
    "Domain": "https://smountprivacy.blogspot.com/",
    "seller_type": "PUBLISHER"
  },
  {
    "Seller_id": 2263,
    "Name": "WM -WM",
    "Domain": "https://pubmatica.blogspot.com/",
    "seller_type": "PUBLISHER"
  }
 ]
}